jik_app/__init__.py
jik_app/py.typed
jik_app-0.0.2.dist-info/METADATA
jik_app-0.0.2.dist-info/WHEEL
jik_app-0.0.2.dist-info/RECORD
